{
  "id": "orch-11-direct-fulfilment-compare",
  "name": "Direct Fulfilment — Compare Options",
  "description": "User directly asks to compare options after analysis exists. The orchestrator should fulfil the request directly (explain_results or inline comparison) — not ask clarifying questions first.",
  "stage": "evaluate",
  "user_message": "Compare the options for me.",
  "canonical_state": {
    "winner": { "id": "opt_raise", "label": "Raise Prices", "win_probability": 0.54 },
    "runner_up": { "id": "opt_volume", "label": "Volume Growth", "win_probability": 0.46 },
    "margin": 0.04,
    "robustness": "fragile",
    "top_drivers": [
      { "factor_id": "fac_conversion", "factor_label": "Conversion Rate", "sensitivity_pct": 38 },
      { "factor_id": "fac_churn", "factor_label": "Churn Rate", "sensitivity_pct": 27 }
    ]
  },
  "graph_context": {
    "nodes": [
      { "id": "goal_mrr", "kind": "goal", "label": "£20k MRR" },
      { "id": "fac_conversion", "kind": "factor", "label": "Conversion Rate", "category": "observable" },
      { "id": "fac_churn", "kind": "factor", "label": "Churn Rate", "category": "observable" },
      { "id": "opt_raise", "kind": "option", "label": "Raise Prices" },
      { "id": "opt_volume", "kind": "option", "label": "Volume Growth" }
    ],
    "edges": [
      { "from": "fac_conversion", "to": "goal_mrr", "strength": { "mean": 0.5, "std": 0.15 }, "exists_probability": 0.9 },
      { "from": "fac_churn", "to": "goal_mrr", "strength": { "mean": -0.4, "std": 0.1 }, "exists_probability": 0.95 }
    ]
  },
  "expected": {
    "expected_tool": null,
    "expects_coaching": false,
    "min_actions": 0,
    "max_actions": 2,
    "banned_terms_checked": true,
    "expects_uncertainty_language": true,
    "forbidden_phrases": ["What would you like to compare", "Could you be more specific", "Which aspects"]
  }
}
